plantao_noticias_b3/__init__.py
plantao_noticias_b3/news_functions.py
plantao_noticias_b3-0.1.1.dist-info/LICENSE.txt
plantao_noticias_b3-0.1.1.dist-info/METADATA
plantao_noticias_b3-0.1.1.dist-info/WHEEL
plantao_noticias_b3-0.1.1.dist-info/RECORD
